Metadata-Version: 2.1
Name: alfonscli
Version: 0.0.1
Summary: A package for simple interaction with Alfons
Home-page: https://github.com/ntoonio/AlfonsCLI.git
Author: Anton Lindroth
Author-email: ntoonio@gmail.com
License: UNKNOWN
Platform: UNKNOWN
